{
    "$schema": "https://turbo.build/schema.json",
    "pipeline": {
        "dev": {
            "cache": false,
            "dependsOn": [
                "^build"
            ]
        },
        "build": {
            "dependsOn": [
                "^build"
            ],
            "outputs": [
                "dist/**"
            ]
        },
        "test": {
            "outputs": [],
            "inputs": [
                "src/**/*.tsx",
                "src/**/*.ts"
            ]
        },
        "lint": {
            "outputs": []
        },
        "type-check": {
            "outputs": [
                "dist/**"
            ]
        }
    }
}